hfut/__init__.py
hfut/exception.py
hfut/interface.py
hfut/log.py
hfut/parser.py
hfut/session.py
hfut/shortcut.py
hfut/util.py
hfut/value.py
hfut-2.2.3.dist-info/DESCRIPTION.rst
hfut-2.2.3.dist-info/METADATA
hfut-2.2.3.dist-info/RECORD
hfut-2.2.3.dist-info/WHEEL
hfut-2.2.3.dist-info/metadata.json
hfut-2.2.3.dist-info/top_level.txt
tests/__init__.py
tests/conftest.py
tests/test_log.py
tests/test_parser.py
tests/test_session.py
tests/test_shortcut.py
tests/test_util.py
