Metadata-Version: 2.0
Name: hfut
Version: 2.2.3
Summary: 
Requires-Dist: beautifulsoup4 (>=4.5.0)
Requires-Dist: requests (>=2.10.0)
Requires-Dist: six (>=1.10.0)
Provides-Extra: ical
Requires-Dist: icalendar (>=3.10); extra == 'ical'
